[{"rank": 1, "athlete_id": 372431, "moving_time": 99382, "num_activities": 7, "distance": 553732.88671875, "elev_gain": 8185.0, "athlete_firstname": "Urs", "athlete_lastname": "H.", "athlete_picture_url": "/assets/avatar/athlete/medium.png", "athlete_member_type": null}, {"rank": 2, "athlete_id": 16756310, "moving_time": 96746, "num_activities": 10, "distance": 538982.3999023438, "elev_gain": 7450.288154602051, "athlete_firstname": "Sepp", "athlete_lastname": "F.", "athlete_picture_url": "/assets/avatar/athlete/medium.png", "athlete_member_type": null}, {"rank": 3, "athlete_id": 22440929, "moving_time": 80604, "num_activities": 7, "distance": 617152.37109375, "elev_gain": 9026.0, "athlete_firstname": "Peider", "athlete_lastname": "N.", "athlete_picture_url": "/assets/avatar/athlete/medium.png", "athlete_member_type": null}, {"rank": 4, "athlete_id": 25457664, "moving_time": 75397, "num_activities": 13, "distance": 281311.6025390625, "elev_gain": 6331.0, "athlete_firstname": "Peter", "athlete_lastname": "P.", "athlete_picture_url": "/assets/avatar/athlete/medium.png", "athlete_member_type": null}, {"rank": 5, "athlete_id": 15992918, "moving_time": 74646, "num_activities": 7, "distance": 213873.82763671875, "elev_gain": 2642.0, "athlete_firstname": "Steve", "athlete_lastname": "C.", "athlete_picture_url": "/assets/avatar/athlete/medium.png", "athlete_member_type": null}, {"rank": 6, "athlete_id": 29514203, "moving_time": 70820, "num_activities": 7, "distance": 336205.2392578125, "elev_gain": 6402.832580566406, "athlete_firstname": "Vroni", "athlete_lastname": "S.", "athlete_picture_url": "/assets/avatar/athlete/medium.png", "athlete_member_type": null}, {"rank": 7, "athlete_id": 55489726, "moving_time": 64747, "num_activities": 14, "distance": 318400.9951171875, "elev_gain": 3525.0, "athlete_firstname": "Dominic", "athlete_lastname": "S.", "athlete_picture_url": "/assets/avatar/athlete/medium.png", "athlete_member_type": null}, {"rank": 8, "athlete_id": 51597919, "moving_time": 64325, "num_activities": 14, "distance": 398339.39544677734, "elev_gain": 2490.4331402778625, "athlete_firstname": "Nicolas", "athlete_lastname": "S.", "athlete_picture_url": "/assets/avatar/athlete/medium.png", "athlete_member_type": null}, {"rank": 9, "athlete_id": 49060784, "moving_time": 61141, "num_activities": 10, "distance": 383651.50390625, "elev_gain": 4002.9889526367188, "athlete_firstname": "Mathias", "athlete_lastname": "B.", "athlete_picture_url": "/assets/avatar/athlete/medium.png", "athlete_member_type": null}, {"rank": 10, "athlete_id": 43717966, "moving_time": 61066, "num_activities": 8, "distance": 441805.078125, "elev_gain": 4237.0, "athlete_firstname": "J\u00f6rg", "athlete_lastname": "K.", "athlete_picture_url": "/assets/avatar/athlete/medium.png", "athlete_member_type": null}, {"rank": 11, "athlete_id": 916353, "moving_time": 59955, "num_activities": 9, "distance": 394424.69580078125, "elev_gain": 5258.0, "athlete_firstname": "Georg", "athlete_lastname": "S.", "athlete_picture_url": "/assets/avatar/athlete/medium.png", "athlete_member_type": null}, {"rank": 12, "athlete_id": 14460104, "moving_time": 59383, "num_activities": 9, "distance": 316275.56201171875, "elev_gain": 4678.003257751465, "athlete_firstname": "Szabolcs", "athlete_lastname": "K.", "athlete_picture_url": "/assets/avatar/athlete/medium.png", "athlete_member_type": null}, {"rank": 13, "athlete_id": 7692435, "moving_time": 59292, "num_activities": 14, "distance": 120709.81103515625, "elev_gain": 3169.0, "athlete_firstname": "Ursula", "athlete_lastname": "B.", "athlete_picture_url": "/assets/avatar/athlete/medium.png", "athlete_member_type": null}, {"rank": 14, "athlete_id": 14573315, "moving_time": 55278, "num_activities": 5, "distance": 184217.0, "elev_gain": 5592.0, "athlete_firstname": "Silvia", "athlete_lastname": "P.", "athlete_picture_url": "/assets/avatar/athlete/medium.png", "athlete_member_type": null}, {"rank": 15, "athlete_id": 58984045, "moving_time": 49384, "num_activities": 7, "distance": 251604.19653320312, "elev_gain": 3214.1613006591797, "athlete_firstname": "Marc", "athlete_lastname": "R.", "athlete_picture_url": "/assets/avatar/athlete/medium.png", "athlete_member_type": null}, {"rank": 16, "athlete_id": 84269972, "moving_time": 48788, "num_activities": 4, "distance": 379394.333984375, "elev_gain": 3766.0, "athlete_firstname": "Blue", "athlete_lastname": "L.", "athlete_picture_url": "/assets/avatar/athlete/medium.png", "athlete_member_type": null}, {"rank": 17, "athlete_id": 18050383, "moving_time": 47515, "num_activities": 5, "distance": 351252.5380859375, "elev_gain": 1710.0, "athlete_firstname": "Rolf", "athlete_lastname": "D.", "athlete_picture_url": "/assets/avatar/athlete/medium.png", "athlete_member_type": null}, {"rank": 18, "athlete_id": 28885166, "moving_time": 45811, "num_activities": 4, "distance": 311860.875, "elev_gain": 4882.0, "athlete_firstname": "P\u00e4sche", "athlete_lastname": "U.", "athlete_picture_url": "/assets/avatar/athlete/medium.png", "athlete_member_type": null}, {"rank": 19, "athlete_id": 4389216, "moving_time": 44918, "num_activities": 10, "distance": 274427.77978515625, "elev_gain": 3935.0, "athlete_firstname": "Samuel", "athlete_lastname": "J.", "athlete_picture_url": "/assets/avatar/athlete/medium.png", "athlete_member_type": null}, {"rank": 20, "athlete_id": 52048655, "moving_time": 43534, "num_activities": 17, "distance": 151631.2508544922, "elev_gain": 472.6000156402588, "athlete_firstname": "Kla", "athlete_lastname": "B.", "athlete_picture_url": "/assets/avatar/athlete/medium.png", "athlete_member_type": null}, {"rank": 21, "athlete_id": 661867, "moving_time": 42750, "num_activities": 10, "distance": 312716.580078125, "elev_gain": 1366.0, "athlete_firstname": "Hang", "athlete_lastname": "L.", "athlete_picture_url": "/assets/avatar/athlete/medium.png", "athlete_member_type": null}, {"rank": 22, "athlete_id": 14946812, "moving_time": 42080, "num_activities": 10, "distance": 308554.8859863281, "elev_gain": 3664.870048522949, "athlete_firstname": "Peter", "athlete_lastname": "M.", "athlete_picture_url": "/assets/avatar/athlete/medium.png", "athlete_member_type": null}, {"rank": 23, "athlete_id": 24834013, "moving_time": 41819, "num_activities": 9, "distance": 274214.5927734375, "elev_gain": 2131.0, "athlete_firstname": "Max", "athlete_lastname": "B.", "athlete_picture_url": "/assets/avatar/athlete/medium.png", "athlete_member_type": null}, {"rank": 24, "athlete_id": 12378132, "moving_time": 41702, "num_activities": 9, "distance": 326469.404296875, "elev_gain": 3594.0, "athlete_firstname": "Francesco", "athlete_lastname": "S.", "athlete_picture_url": "/assets/avatar/athlete/medium.png", "athlete_member_type": null}, {"rank": 25, "athlete_id": 7534298, "moving_time": 41556, "num_activities": 4, "distance": 238314.4111328125, "elev_gain": 1790.5004806518555, "athlete_firstname": "Marcel", "athlete_lastname": "I.", "athlete_picture_url": "/assets/avatar/athlete/medium.png", "athlete_member_type": null}, {"rank": 26, "athlete_id": 23122456, "moving_time": 41184, "num_activities": 6, "distance": 386438.4765625, "elev_gain": 1830.0, "athlete_firstname": "Stephan", "athlete_lastname": "W.", "athlete_picture_url": "/assets/avatar/athlete/medium.png", "athlete_member_type": null}, {"rank": 27, "athlete_id": 3961577, "moving_time": 40175, "num_activities": 8, "distance": 140392.19653320312, "elev_gain": 4190.496229171753, "athlete_firstname": "Peter", "athlete_lastname": "K.", "athlete_picture_url": "/assets/avatar/athlete/medium.png", "athlete_member_type": null}, {"rank": 28, "athlete_id": 4471900, "moving_time": 37972, "num_activities": 10, "distance": 272716.71875, "elev_gain": 2656.8427124023438, "athlete_firstname": "Rainer", "athlete_lastname": "B.", "athlete_picture_url": "/assets/avatar/athlete/medium.png", "athlete_member_type": null}, {"rank": 29, "athlete_id": 60467988, "moving_time": 37514, "num_activities": 8, "distance": 187228.0, "elev_gain": 1584.0, "athlete_firstname": "Flurin", "athlete_lastname": "H.", "athlete_picture_url": "/assets/avatar/athlete/medium.png", "athlete_member_type": null}, {"rank": 30, "athlete_id": 22347544, "moving_time": 36697, "num_activities": 5, "distance": 138194.53125, "elev_gain": 2045.0, "athlete_firstname": "Unggle", "athlete_lastname": "T.", "athlete_picture_url": "/assets/avatar/athlete/medium.png", "athlete_member_type": null}, {"rank": 31, "athlete_id": 22053367, "moving_time": 34150, "num_activities": 10, "distance": 298299.4501953125, "elev_gain": 2341.0, "athlete_firstname": "Roger", "athlete_lastname": "K.", "athlete_picture_url": "/assets/avatar/athlete/medium.png", "athlete_member_type": null}, {"rank": 32, "athlete_id": 56992126, "moving_time": 34107, "num_activities": 8, "distance": 49242.66015625, "elev_gain": 233.0, "athlete_firstname": "Corinne", "athlete_lastname": "Z.", "athlete_picture_url": "/assets/avatar/athlete/medium.png", "athlete_member_type": null}, {"rank": 33, "athlete_id": 8718070, "moving_time": 33723, "num_activities": 3, "distance": 232432.7548828125, "elev_gain": 2789.0, "athlete_firstname": "Peter", "athlete_lastname": "S.", "athlete_picture_url": "/assets/avatar/athlete/medium.png", "athlete_member_type": null}, {"rank": 34, "athlete_id": 4722924, "moving_time": 32999, "num_activities": 4, "distance": 275561.49609375, "elev_gain": 4656.0, "athlete_firstname": "Markus", "athlete_lastname": "R.", "athlete_picture_url": "/assets/avatar/athlete/medium.png", "athlete_member_type": null}, {"rank": 35, "athlete_id": 57591751, "moving_time": 32830, "num_activities": 13, "distance": 140531.69775390625, "elev_gain": 1743.635648727417, "athlete_firstname": "Peter", "athlete_lastname": "P.", "athlete_picture_url": "/assets/avatar/athlete/medium.png", "athlete_member_type": null}, {"rank": 36, "athlete_id": 6200327, "moving_time": 32325, "num_activities": 7, "distance": 265846.14453125, "elev_gain": 2779.0, "athlete_firstname": "The", "athlete_lastname": "M.", "athlete_picture_url": "/assets/avatar/athlete/medium.png", "athlete_member_type": null}, {"rank": 37, "athlete_id": 10843886, "moving_time": 31396, "num_activities": 7, "distance": 160328.9833984375, "elev_gain": 1675.0, "athlete_firstname": "Philippe", "athlete_lastname": "K.", "athlete_picture_url": "/assets/avatar/athlete/medium.png", "athlete_member_type": null}, {"rank": 38, "athlete_id": 34543396, "moving_time": 30405, "num_activities": 7, "distance": 202171.798828125, "elev_gain": 1936.3999824523926, "athlete_firstname": "Michael", "athlete_lastname": "C.", "athlete_picture_url": "/assets/avatar/athlete/medium.png", "athlete_member_type": null}, {"rank": 39, "athlete_id": 8597909, "moving_time": 30380, "num_activities": 2, "distance": 192058.2109375, "elev_gain": 4301.0, "athlete_firstname": "lukas", "athlete_lastname": "b.", "athlete_picture_url": "/assets/avatar/athlete/medium.png", "athlete_member_type": null}, {"rank": 40, "athlete_id": 656368, "moving_time": 30304, "num_activities": 4, "distance": 180471.06640625, "elev_gain": 2257.0, "athlete_firstname": "Kai", "athlete_lastname": "S.", "athlete_picture_url": "/assets/avatar/athlete/medium.png", "athlete_member_type": null}, {"rank": 41, "athlete_id": 29737160, "moving_time": 30147, "num_activities": 7, "distance": 108577.21826171875, "elev_gain": 1133.0, "athlete_firstname": "Urs", "athlete_lastname": "S.", "athlete_picture_url": "/assets/avatar/athlete/medium.png", "athlete_member_type": null}, {"rank": 42, "athlete_id": 5959692, "moving_time": 29987, "num_activities": 6, "distance": 243902.857421875, "elev_gain": 1683.0, "athlete_firstname": "El Leo", "athlete_lastname": "T.", "athlete_picture_url": "/assets/avatar/athlete/medium.png", "athlete_member_type": null}, {"rank": 43, "athlete_id": 3379, "moving_time": 29977, "num_activities": 7, "distance": 119434.63037109375, "elev_gain": 935.0, "athlete_firstname": "Erik", "athlete_lastname": "W.", "athlete_picture_url": "/assets/avatar/athlete/medium.png", "athlete_member_type": null}, {"rank": 44, "athlete_id": 10450712, "moving_time": 29065, "num_activities": 2, "distance": 198889.83203125, "elev_gain": 2423.0, "athlete_firstname": "Carlo", "athlete_lastname": "B.", "athlete_picture_url": "/assets/avatar/athlete/medium.png", "athlete_member_type": null}, {"rank": 45, "athlete_id": 31956795, "moving_time": 29014, "num_activities": 5, "distance": 206427.728515625, "elev_gain": 2135.387939453125, "athlete_firstname": "Oli", "athlete_lastname": "\ud83c\udde8.", "athlete_picture_url": "/assets/avatar/athlete/medium.png", "athlete_member_type": null}, {"rank": 46, "athlete_id": 35426250, "moving_time": 28272, "num_activities": 4, "distance": 202693.955078125, "elev_gain": 2270.0680084228516, "athlete_firstname": "Urs", "athlete_lastname": "J.", "athlete_picture_url": "/assets/avatar/athlete/medium.png", "athlete_member_type": null}, {"rank": 47, "athlete_id": 36601258, "moving_time": 28200, "num_activities": 8, "distance": 146914.44091796875, "elev_gain": 2570.2429161071777, "athlete_firstname": "Christian", "athlete_lastname": "K.", "athlete_picture_url": "/assets/avatar/athlete/medium.png", "athlete_member_type": null}, {"rank": 48, "athlete_id": 28008297, "moving_time": 28144, "num_activities": 6, "distance": 140596.861328125, "elev_gain": 1924.5211334228516, "athlete_firstname": "Alexander", "athlete_lastname": "B.", "athlete_picture_url": "/assets/avatar/athlete/medium.png", "athlete_member_type": null}, {"rank": 49, "athlete_id": 11422737, "moving_time": 26768, "num_activities": 6, "distance": 147498.79663085938, "elev_gain": 2530.5151176452637, "athlete_firstname": "Schribi", "athlete_lastname": "d.", "athlete_picture_url": "/assets/avatar/athlete/medium.png", "athlete_member_type": null}, {"rank": 50, "athlete_id": 8923478, "moving_time": 25843, "num_activities": 8, "distance": 108856.2802734375, "elev_gain": 2678.7115173339844, "athlete_firstname": "Mateo", "athlete_lastname": "P.", "athlete_picture_url": "/assets/avatar/athlete/medium.png", "athlete_member_type": null}, {"rank": 51, "athlete_id": 355767, "moving_time": 25321, "num_activities": 7, "distance": 73552.10986328125, "elev_gain": 154.87045574188232, "athlete_firstname": "Jan-Hein", "athlete_lastname": "v.", "athlete_picture_url": "/assets/avatar/athlete/medium.png", "athlete_member_type": null}, {"rank": 52, "athlete_id": 6771401, "moving_time": 24884, "num_activities": 7, "distance": 206303.740234375, "elev_gain": 931.0, "athlete_firstname": "Rolf", "athlete_lastname": "L.", "athlete_picture_url": "/assets/avatar/athlete/medium.png", "athlete_member_type": null}, {"rank": 53, "athlete_id": 9268147, "moving_time": 24243, "num_activities": 8, "distance": 144403.357421875, "elev_gain": 1629.6320190429688, "athlete_firstname": "Polter", "athlete_lastname": "G.", "athlete_picture_url": "/assets/avatar/athlete/medium.png", "athlete_member_type": null}, {"rank": 54, "athlete_id": 15227054, "moving_time": 24192, "num_activities": 6, "distance": 257043.216796875, "elev_gain": 0.0, "athlete_firstname": "Markus", "athlete_lastname": "A.", "athlete_picture_url": "/assets/avatar/athlete/medium.png", "athlete_member_type": null}, {"rank": 55, "athlete_id": 24260024, "moving_time": 24017, "num_activities": 1, "distance": 118377.703125, "elev_gain": 2642.0, "athlete_firstname": "Irakli", "athlete_lastname": "J.", "athlete_picture_url": "/assets/avatar/athlete/medium.png", "athlete_member_type": null}, {"rank": 56, "athlete_id": 32745649, "moving_time": 23953, "num_activities": 7, "distance": 58973.599609375, "elev_gain": 363.3502082824707, "athlete_firstname": "Fritz", "athlete_lastname": "R.", "athlete_picture_url": "/assets/avatar/athlete/medium.png", "athlete_member_type": null}, {"rank": 57, "athlete_id": 6991554, "moving_time": 23035, "num_activities": 4, "distance": 118767.9921875, "elev_gain": 2195.0, "athlete_firstname": "Mike", "athlete_lastname": "\ud83c\udfb2.", "athlete_picture_url": "/assets/avatar/athlete/medium.png", "athlete_member_type": null}, {"rank": 58, "athlete_id": 16736549, "moving_time": 23026, "num_activities": 10, "distance": 100656.0, "elev_gain": 1465.0, "athlete_firstname": "Pascal", "athlete_lastname": "B.", "athlete_picture_url": "/assets/avatar/athlete/medium.png", "athlete_member_type": null}, {"rank": 59, "athlete_id": 65173763, "moving_time": 21907, "num_activities": 4, "distance": 109391.849609375, "elev_gain": 1829.0, "athlete_firstname": "Christine", "athlete_lastname": "B.", "athlete_picture_url": "/assets/avatar/athlete/medium.png", "athlete_member_type": null}, {"rank": 60, "athlete_id": 15647252, "moving_time": 21776, "num_activities": 5, "distance": 36319.16015625, "elev_gain": 860.0, "athlete_firstname": "Karsten", "athlete_lastname": "S.", "athlete_picture_url": "/assets/avatar/athlete/medium.png", "athlete_member_type": null}, {"rank": 61, "athlete_id": 55821041, "moving_time": 21529, "num_activities": 3, "distance": 135135.8515625, "elev_gain": 1670.0, "athlete_firstname": "Lucas", "athlete_lastname": "W.", "athlete_picture_url": "/assets/avatar/athlete/medium.png", "athlete_member_type": null}, {"rank": 62, "athlete_id": 5329940, "moving_time": 21191, "num_activities": 5, "distance": 69641.091796875, "elev_gain": 1073.0, "athlete_firstname": "Alexander", "athlete_lastname": "R.", "athlete_picture_url": "/assets/avatar/athlete/medium.png", "athlete_member_type": null}, {"rank": 63, "athlete_id": 21995947, "moving_time": 19621, "num_activities": 3, "distance": 74012.95947265625, "elev_gain": 1222.0, "athlete_firstname": "Paulo", "athlete_lastname": "A.", "athlete_picture_url": "/assets/avatar/athlete/medium.png", "athlete_member_type": null}, {"rank": 64, "athlete_id": 8800165, "moving_time": 19351, "num_activities": 4, "distance": 109345.3408203125, "elev_gain": 623.1784553527832, "athlete_firstname": "A.", "athlete_lastname": "G.", "athlete_picture_url": "/assets/avatar/athlete/medium.png", "athlete_member_type": null}, {"rank": 65, "athlete_id": 2253832, "moving_time": 19125, "num_activities": 4, "distance": 123155.0986328125, "elev_gain": 765.0, "athlete_firstname": "Ueli", "athlete_lastname": "B.", "athlete_picture_url": "/assets/avatar/athlete/medium.png", "athlete_member_type": null}, {"rank": 66, "athlete_id": 22320060, "moving_time": 18911, "num_activities": 5, "distance": 108143.9482421875, "elev_gain": 1350.0, "athlete_firstname": "Petra", "athlete_lastname": "S.", "athlete_picture_url": "/assets/avatar/athlete/medium.png", "athlete_member_type": null}, {"rank": 67, "athlete_id": 2851278, "moving_time": 18736, "num_activities": 2, "distance": 122928.51171875, "elev_gain": 1257.0, "athlete_firstname": "Ludovic Innocent", "athlete_lastname": "V.", "athlete_picture_url": "/assets/avatar/athlete/medium.png", "athlete_member_type": null}, {"rank": 68, "athlete_id": 42768485, "moving_time": 18697, "num_activities": 3, "distance": 124920.2421875, "elev_gain": 1143.6999969482422, "athlete_firstname": "Flipper", "athlete_lastname": "F.", "athlete_picture_url": "/assets/avatar/athlete/medium.png", "athlete_member_type": null}, {"rank": 69, "athlete_id": 9681288, "moving_time": 18675, "num_activities": 5, "distance": 73109.4921875, "elev_gain": 1001.8990173339844, "athlete_firstname": "Reto", "athlete_lastname": "S.", "athlete_picture_url": "/assets/avatar/athlete/medium.png", "athlete_member_type": null}, {"rank": 70, "athlete_id": 9091538, "moving_time": 18526, "num_activities": 5, "distance": 121750.087890625, "elev_gain": 1934.0, "athlete_firstname": "Vince", "athlete_lastname": "L.", "athlete_picture_url": "/assets/avatar/athlete/medium.png", "athlete_member_type": null}, {"rank": 71, "athlete_id": 5917457, "moving_time": 18444, "num_activities": 4, "distance": 121381.66796875, "elev_gain": 1701.0, "athlete_firstname": "Armando", "athlete_lastname": "P.", "athlete_picture_url": "/assets/avatar/athlete/medium.png", "athlete_member_type": null}, {"rank": 72, "athlete_id": 71754696, "moving_time": 18269, "num_activities": 2, "distance": 112740.55078125, "elev_gain": 1410.0, "athlete_firstname": "Vincenzo", "athlete_lastname": "R.", "athlete_picture_url": "/assets/avatar/athlete/medium.png", "athlete_member_type": null}, {"rank": 73, "athlete_id": 3045449, "moving_time": 17042, "num_activities": 3, "distance": 105252.75537109375, "elev_gain": 1425.0, "athlete_firstname": "H\u00f6ge", "athlete_lastname": "F.", "athlete_picture_url": "/assets/avatar/athlete/medium.png", "athlete_member_type": null}, {"rank": 74, "athlete_id": 4654968, "moving_time": 16595, "num_activities": 5, "distance": 57452.0, "elev_gain": 1056.0, "athlete_firstname": "Gabriel", "athlete_lastname": "L.", "athlete_picture_url": "/assets/avatar/athlete/medium.png", "athlete_member_type": null}, {"rank": 75, "athlete_id": 58050107, "moving_time": 16508, "num_activities": 1, "distance": 135361.703125, "elev_gain": 828.0, "athlete_firstname": "\ud83c\udde8\ud83c\udded Pascal", "athlete_lastname": "M.", "athlete_picture_url": "/assets/avatar/athlete/medium.png", "athlete_member_type": null}, {"rank": 76, "athlete_id": 36659794, "moving_time": 16488, "num_activities": 5, "distance": 135171.259765625, "elev_gain": 951.0, "athlete_firstname": "Ale", "athlete_lastname": "E.", "athlete_picture_url": "/assets/avatar/athlete/medium.png", "athlete_member_type": null}, {"rank": 77, "athlete_id": 51063087, "moving_time": 16415, "num_activities": 2, "distance": 101512.5859375, "elev_gain": 1102.0, "athlete_firstname": "Simone", "athlete_lastname": "C.", "athlete_picture_url": "/assets/avatar/athlete/medium.png", "athlete_member_type": null}, {"rank": 78, "athlete_id": 3980614, "moving_time": 15909, "num_activities": 4, "distance": 103058.81787109375, "elev_gain": 1092.0857849121094, "athlete_firstname": "Fabian", "athlete_lastname": "J.", "athlete_picture_url": "/assets/avatar/athlete/medium.png", "athlete_member_type": null}, {"rank": 79, "athlete_id": 5964350, "moving_time": 15660, "num_activities": 3, "distance": 120500.0, "elev_gain": 0.0, "athlete_firstname": "Andrea", "athlete_lastname": "G.", "athlete_picture_url": "/assets/avatar/athlete/medium.png", "athlete_member_type": null}, {"rank": 80, "athlete_id": 21617593, "moving_time": 15659, "num_activities": 1, "distance": 80051.5546875, "elev_gain": 1348.0, "athlete_firstname": "Peter", "athlete_lastname": "S.", "athlete_picture_url": "/assets/avatar/athlete/medium.png", "athlete_member_type": null}, {"rank": 81, "athlete_id": 45978227, "moving_time": 15605, "num_activities": 3, "distance": 89630.796875, "elev_gain": 1122.8162994384766, "athlete_firstname": "Vincenzo", "athlete_lastname": "B.", "athlete_picture_url": "/assets/avatar/athlete/medium.png", "athlete_member_type": null}, {"rank": 82, "athlete_id": 18791735, "moving_time": 15433, "num_activities": 4, "distance": 111376.69140625, "elev_gain": 906.0, "athlete_firstname": "365_", "athlete_lastname": "e.", "athlete_picture_url": "/assets/avatar/athlete/medium.png", "athlete_member_type": null}, {"rank": 83, "athlete_id": 14580627, "moving_time": 14705, "num_activities": 5, "distance": 87935.1083984375, "elev_gain": 1070.0, "athlete_firstname": "Yves", "athlete_lastname": "L.", "athlete_picture_url": "/assets/avatar/athlete/medium.png", "athlete_member_type": null}, {"rank": 84, "athlete_id": 6807078, "moving_time": 14076, "num_activities": 3, "distance": 115226.900390625, "elev_gain": 639.0, "athlete_firstname": "Matthias", "athlete_lastname": "K.", "athlete_picture_url": "/assets/avatar/athlete/medium.png", "athlete_member_type": null}, {"rank": 85, "athlete_id": 549334, "moving_time": 13851, "num_activities": 2, "distance": 90692.5068359375, "elev_gain": 1198.0, "athlete_firstname": "Matthias", "athlete_lastname": "B.", "athlete_picture_url": "/assets/avatar/athlete/medium.png", "athlete_member_type": null}, {"rank": 86, "athlete_id": 12465921, "moving_time": 13473, "num_activities": 3, "distance": 70610.3798828125, "elev_gain": 816.0, "athlete_firstname": "Michael", "athlete_lastname": "I.", "athlete_picture_url": "/assets/avatar/athlete/medium.png", "athlete_member_type": null}, {"rank": 87, "athlete_id": 93451214, "moving_time": 12957, "num_activities": 3, "distance": 40924.4912109375, "elev_gain": 237.0984344482422, "athlete_firstname": "Maria", "athlete_lastname": "E.", "athlete_picture_url": "/assets/avatar/athlete/medium.png", "athlete_member_type": null}, {"rank": 88, "athlete_id": 50903344, "moving_time": 12611, "num_activities": 1, "distance": 80472.6484375, "elev_gain": 197.6690673828125, "athlete_firstname": "Leo", "athlete_lastname": "S.", "athlete_picture_url": "/assets/avatar/athlete/medium.png", "athlete_member_type": null}, {"rank": 89, "athlete_id": 12257960, "moving_time": 11960, "num_activities": 8, "distance": 44850.719665527344, "elev_gain": 144.0, "athlete_firstname": "Macchese", "athlete_lastname": "D.", "athlete_picture_url": "/assets/avatar/athlete/medium.png", "athlete_member_type": null}, {"rank": 90, "athlete_id": 10922055, "moving_time": 11764, "num_activities": 4, "distance": 90541.138671875, "elev_gain": 497.0, "athlete_firstname": "\ud83c\udde8\ud83c\udded jay", "athlete_lastname": "h.", "athlete_picture_url": "/assets/avatar/athlete/medium.png", "athlete_member_type": null}, {"rank": 91, "athlete_id": 2262629, "moving_time": 11485, "num_activities": 4, "distance": 30197.638916015625, "elev_gain": 703.5625295639038, "athlete_firstname": "John", "athlete_lastname": "N.", "athlete_picture_url": "/assets/avatar/athlete/medium.png", "athlete_member_type": null}, {"rank": 92, "athlete_id": 33189628, "moving_time": 10556, "num_activities": 2, "distance": 41038.03125, "elev_gain": 876.0, "athlete_firstname": "Reto", "athlete_lastname": "W.", "athlete_picture_url": "/assets/avatar/athlete/medium.png", "athlete_member_type": null}, {"rank": 93, "athlete_id": 16030256, "moving_time": 9956, "num_activities": 3, "distance": 65051.3134765625, "elev_gain": 769.0, "athlete_firstname": "Nadja", "athlete_lastname": "K.", "athlete_picture_url": "/assets/avatar/athlete/medium.png", "athlete_member_type": null}, {"rank": 94, "athlete_id": 93452899, "moving_time": 7954, "num_activities": 3, "distance": 27555.0009765625, "elev_gain": 264.0, "athlete_firstname": "Marco", "athlete_lastname": "G.", "athlete_picture_url": "/assets/avatar/athlete/medium.png", "athlete_member_type": null}, {"rank": 95, "athlete_id": 7070994, "moving_time": 7323, "num_activities": 1, "distance": 31399.83984375, "elev_gain": 639.0, "athlete_firstname": "Waldemar", "athlete_lastname": "D.", "athlete_picture_url": "/assets/avatar/athlete/medium.png", "athlete_member_type": null}, {"rank": 96, "athlete_id": 18926488, "moving_time": 7245, "num_activities": 1, "distance": 0.0, "elev_gain": 0.0, "athlete_firstname": "Adrian", "athlete_lastname": "G.", "athlete_picture_url": "/assets/avatar/athlete/medium.png", "athlete_member_type": null}, {"rank": 97, "athlete_id": 10098982, "moving_time": 6798, "num_activities": 3, "distance": 9784.7099609375, "elev_gain": 107.0, "athlete_firstname": "Remo", "athlete_lastname": "M.", "athlete_picture_url": "/assets/avatar/athlete/medium.png", "athlete_member_type": null}, {"rank": 98, "athlete_id": 4143694, "moving_time": 6349, "num_activities": 2, "distance": 40575.1796875, "elev_gain": 535.0, "athlete_firstname": "Stefan", "athlete_lastname": "S.", "athlete_picture_url": "/assets/avatar/athlete/medium.png", "athlete_member_type": null}, {"rank": 99, "athlete_id": 2116373, "moving_time": 6116, "num_activities": 1, "distance": 44388.87890625, "elev_gain": 312.0, "athlete_firstname": "David", "athlete_lastname": "H.", "athlete_picture_url": "/assets/avatar/athlete/medium.png", "athlete_member_type": null}, {"rank": 100, "athlete_id": 56556015, "moving_time": 4626, "num_activities": 1, "distance": 10201.8603515625, "elev_gain": 729.0, "athlete_firstname": "Marion", "athlete_lastname": "B.", "athlete_picture_url": "/assets/avatar/athlete/medium.png", "athlete_member_type": null}, {"rank": 101, "athlete_id": 35288286, "moving_time": 3968, "num_activities": 1, "distance": 10384.0, "elev_gain": 49.0, "athlete_firstname": "Annabelle", "athlete_lastname": "M.", "athlete_picture_url": "/assets/avatar/athlete/medium.png", "athlete_member_type": null}, {"rank": 102, "athlete_id": 2080027, "moving_time": 3749, "num_activities": 1, "distance": 13514.2998046875, "elev_gain": 1.0, "athlete_firstname": "Silvia", "athlete_lastname": "B.", "athlete_picture_url": "/assets/avatar/athlete/medium.png", "athlete_member_type": null}, {"rank": 103, "athlete_id": 24534245, "moving_time": 2931, "num_activities": 1, "distance": 8916.900390625, "elev_gain": 70.85049438476562, "athlete_firstname": "Sandro", "athlete_lastname": "T.", "athlete_picture_url": "/assets/avatar/athlete/medium.png", "athlete_member_type": null}, {"rank": 104, "athlete_id": 17065165, "moving_time": 2920, "num_activities": 2, "distance": 47485.83203125, "elev_gain": 4.0, "athlete_firstname": "Daniel", "athlete_lastname": "M.", "athlete_picture_url": "/assets/avatar/athlete/medium.png", "athlete_member_type": null}, {"rank": 105, "athlete_id": 22643351, "moving_time": 2736, "num_activities": 2, "distance": 0.0, "elev_gain": 0.0, "athlete_firstname": "Andrea", "athlete_lastname": "L.", "athlete_picture_url": "/assets/avatar/athlete/medium.png", "athlete_member_type": null}, {"rank": 106, "athlete_id": 51461026, "moving_time": 2408, "num_activities": 1, "distance": 7857.5, "elev_gain": 32.0, "athlete_firstname": "olivia", "athlete_lastname": "K.", "athlete_picture_url": "/assets/avatar/athlete/medium.png", "athlete_member_type": null}, {"rank": 107, "athlete_id": 57172117, "moving_time": 1364, "num_activities": 1, "distance": 1930.47998046875, "elev_gain": 12.0, "athlete_firstname": "Marco", "athlete_lastname": "J.", "athlete_picture_url": "/assets/avatar/athlete/medium.png", "athlete_member_type": null}]